gke_deployment_tools/__init__.py
gke_deployment_tools/deployment_tools.py
gke_deployment_tools/deployment_tools2.py
gke_deployment_tools/k8s_client.py
gke_deployment_tools/pyarmor_runtime_000000/__init__.py
gke_deployment_tools-1.0.9.dist-info/licenses/LICENSE
gke_deployment_tools-1.0.9.dist-info/METADATA
gke_deployment_tools-1.0.9.dist-info/WHEEL
gke_deployment_tools-1.0.9.dist-info/top_level.txt
gke_deployment_tools-1.0.9.dist-info/RECORD
