Metadata-Version: 2.4
Name: gke-deployment-tools
Version: 1.0.9
Summary: [Protected] [Protected] GKE Deployment Management Tools with K8s Client Pooling
License: MIT
Project-URL: Homepage, https://github.com/yourusername/gke-deployment-tools
Project-URL: Repository, https://github.com/yourusername/gke-deployment-tools
Keywords: gke,kubernetes,deployment,pod,logs
Classifier: Development Status :: 4 - Beta
Classifier: Intended Audience :: Developers
Classifier: License :: OSI Approved :: MIT License
Classifier: Programming Language :: Python :: 3
Classifier: Programming Language :: Python :: 3.8
Classifier: Programming Language :: Python :: 3.9
Classifier: Programming Language :: Python :: 3.10
Classifier: Programming Language :: Python :: 3.11
Requires-Python: >=3.8
License-File: LICENSE
Requires-Dist: kubernetes>=28.1.0
Requires-Dist: google-cloud-container>=2.30.0
Requires-Dist: google-auth>=2.23.0
Dynamic: license-file
